<I xmlns:xsi="http://www.w3.org/2001/XMLSchema-instance" xmlns:xsd="http://www.w3.org/2001/XMLSchema" c="LootActions" s="3915333828639310249" i="action" m="interactions.utils.loot" n="ADB_confident_loot">
  <L n="loot_actions">
    <V t="buff">
      <U n="buff">
        <U n="buff">
          <T n="buff_type">7570318287540438856<!--ADB_confident_buff--></T>
          <V n="buff_reason" t="enabled">
            <T n="enabled">0xD1988AA7<!--(From wearing a diaper)--></T>
          </V>
        </U>
        <E n="subject">Actor</E>
        <U n="chance">
          <T n="base_chance">20</T>
        </U>
        <L n="tests">
          <L>
            <V t="buff">
              <U n="buff">
                <L n="blacklist">
                  <T>10094<!--buff_Sim_IsSleeping--></T>
                </L>
                <E n="subject">Actor</E>
              </U>
            </V>
            <V t="test_set_reference">
              <T n="test_set_reference">17796732764948000262<!--IwnBedWetting_testSet_HasDiaperEquipped--></T>
            </V>
            <V t="buff">
              <U n="buff">
                <L n="blacklist">
                  <T>14213915589173281387<!--ADB_crinklycantheyhear_buff--></T>
                  <T>7570318287540438856<!--ADB_confident_buff--></T>
                </L>
              </U>
            </V>
          </L>
        </L>
      </U>
    </V>
  </L>
</I>