<I c="LootActions" i="action" m="interactions.utils.loot" n="LilNinthel:loot_statistic_intentional_pants_wettings" s="10616734412670168306">
  <L n="loot_actions">
    <V t="statistics">
      <V n="statistics" t="statistic_change">
        <U n="statistic_change">
          <T n="amount">1</T>
          <T n="stat">16864196793185567039<!--LilNinthel:statistic_intentional_pants_wettings--></T>
          <L n="subject">
            <E>Actor</E>
          </L>
        </U>
      </V>
    </V>
  </L>
</I>